python_boilerplate/__init__.py
python_boilerplate/cli.py
python_boilerplate/python_boilerplate.py
python_boilerplate2-0.1.0.dist-info/DESCRIPTION.rst
python_boilerplate2-0.1.0.dist-info/METADATA
python_boilerplate2-0.1.0.dist-info/RECORD
python_boilerplate2-0.1.0.dist-info/WHEEL
python_boilerplate2-0.1.0.dist-info/entry_points.txt
python_boilerplate2-0.1.0.dist-info/metadata.json
python_boilerplate2-0.1.0.dist-info/top_level.txt
